omnifold/__init__.py
omnifold/dataloader.py
omnifold/net.py
omnifold/omnifold.py
omnifold/utils.py
omnifold/tests/__init__.py
omnifold/tests/test_dataloader.py
omnifold/tests/test_omnifold.py
unbinned_unfold-0.1.8.dist-info/METADATA
unbinned_unfold-0.1.8.dist-info/WHEEL
unbinned_unfold-0.1.8.dist-info/top_level.txt
unbinned_unfold-0.1.8.dist-info/RECORD
