Metadata-Version: 2.1
Name: unbinned_unfold
Version: 0.1.8
Summary: OmniFold, a library to perform unbinned and high-dimensional unfolding for HEP.
Home-page: https://github.com/ViniciusMikuni/omnifold
Author: Vinicius Mikuni
Author-email: vmikuni@lbl.gov
Classifier: Programming Language :: Python :: 3
Classifier: License :: OSI Approved :: MIT License
Classifier: Operating System :: OS Independent
Requires-Python: >=3.6
Requires-Dist: horovod ==0.28.1
Requires-Dist: matplotlib
Requires-Dist: numpy
Requires-Dist: PyYAML
Requires-Dist: setuptools
Requires-Dist: tensorflow
